odoo9_addon_sale_validity-9.0.1.0.0.99.dev10-py3.8-nspkg.pth
odoo_addons/sale_validity/README.rst
odoo_addons/sale_validity/__init__.py
odoo_addons/sale_validity/__openerp__.py
odoo_addons/sale_validity/i18n/am.po
odoo_addons/sale_validity/i18n/ar.po
odoo_addons/sale_validity/i18n/ca.po
odoo_addons/sale_validity/i18n/da.po
odoo_addons/sale_validity/i18n/de.po
odoo_addons/sale_validity/i18n/el_GR.po
odoo_addons/sale_validity/i18n/es.po
odoo_addons/sale_validity/i18n/es_ES.po
odoo_addons/sale_validity/i18n/es_MX.po
odoo_addons/sale_validity/i18n/es_VE.po
odoo_addons/sale_validity/i18n/eu.po
odoo_addons/sale_validity/i18n/fi.po
odoo_addons/sale_validity/i18n/fr.po
odoo_addons/sale_validity/i18n/fr_CA.po
odoo_addons/sale_validity/i18n/fr_FR.po
odoo_addons/sale_validity/i18n/hr.po
odoo_addons/sale_validity/i18n/hr_HR.po
odoo_addons/sale_validity/i18n/hu.po
odoo_addons/sale_validity/i18n/it.po
odoo_addons/sale_validity/i18n/nb.po
odoo_addons/sale_validity/i18n/nb_NO.po
odoo_addons/sale_validity/i18n/nl.po
odoo_addons/sale_validity/i18n/nl_BE.po
odoo_addons/sale_validity/i18n/nl_NL.po
odoo_addons/sale_validity/i18n/pt.po
odoo_addons/sale_validity/i18n/pt_BR.po
odoo_addons/sale_validity/i18n/ro.po
odoo_addons/sale_validity/i18n/sale_validity.pot
odoo_addons/sale_validity/i18n/sk.po
odoo_addons/sale_validity/i18n/sl.po
odoo_addons/sale_validity/i18n/tr.po
odoo_addons/sale_validity/i18n/tr_TR.po
odoo_addons/sale_validity/i18n/vi_VN.po
odoo_addons/sale_validity/i18n/zh_CN.po
odoo_addons/sale_validity/migrations/9.0.1.0.0/pre-migration.py
odoo_addons/sale_validity/models/__init__.py
odoo_addons/sale_validity/models/company.py
odoo_addons/sale_validity/models/sale_order.py
odoo_addons/sale_validity/static/description/company_configuration.png
odoo_addons/sale_validity/static/description/icon.png
odoo_addons/sale_validity/tests/__init__.py
odoo_addons/sale_validity/tests/test_sale_validity.py
odoo_addons/sale_validity/views/res_company_view.xml
odoo9_addon_sale_validity-9.0.1.0.0.99.dev10.dist-info/METADATA
odoo9_addon_sale_validity-9.0.1.0.0.99.dev10.dist-info/WHEEL
odoo9_addon_sale_validity-9.0.1.0.0.99.dev10.dist-info/namespace_packages.txt
odoo9_addon_sale_validity-9.0.1.0.0.99.dev10.dist-info/top_level.txt
odoo9_addon_sale_validity-9.0.1.0.0.99.dev10.dist-info/RECORD
